README.md
setup.cfg
setup.py
eis/__init__.py
eis/discount/__init__.py
eis/discount/api_client.py
eis/discount/configuration.py
eis/discount/exceptions.py
eis/discount/model_utils.py
eis/discount/rest.py
eis/discount/api/__init__.py
eis/discount/api/campaigns_api.py
eis/discount/api/default_api.py
eis/discount/api/policy_vouchers_api.py
eis/discount/api/vouchers_api.py
eis/discount/apis/__init__.py
eis/discount/model/__init__.py
eis/discount/model/campaign_class.py
eis/discount/model/charge_policy_voucher_request_dto.py
eis/discount/model/charge_policy_voucher_response_class.py
eis/discount/model/check_account_eligibility_request_dto.py
eis/discount/model/check_account_eligibility_response_class.py
eis/discount/model/create_campaign_request_dto.py
eis/discount/model/create_campaign_response_class.py
eis/discount/model/create_eligible_account_request_dto.py
eis/discount/model/create_eligible_account_response_class.py
eis/discount/model/create_policy_voucher_request_dto.py
eis/discount/model/create_policy_voucher_response_class.py
eis/discount/model/create_product_discount_dto.py
eis/discount/model/create_voucher_request_dto.py
eis/discount/model/create_voucher_response_class.py
eis/discount/model/eligible_account_class.py
eis/discount/model/get_campaign_response_class.py
eis/discount/model/get_policy_voucher_response_class.py
eis/discount/model/get_voucher_response_class.py
eis/discount/model/inline_response200.py
eis/discount/model/inline_response503.py
eis/discount/model/list_campaigns_response_class.py
eis/discount/model/list_eligible_accounts_response_class.py
eis/discount/model/list_policy_vouchers_response_class.py
eis/discount/model/list_vouchers_response_class.py
eis/discount/model/policy_voucher_class.py
eis/discount/model/policy_voucher_transaction_class.py
eis/discount/model/product_discount_class.py
eis/discount/model/redeem_policy_voucher_request_dto.py
eis/discount/model/redeem_policy_voucher_response_class.py
eis_discount.egg-info/PKG-INFO
eis_discount.egg-info/SOURCES.txt
eis_discount.egg-info/dependency_links.txt
eis_discount.egg-info/requires.txt
eis_discount.egg-info/top_level.txt
