Metadata-Version: 2.1
Name: eis-discount
Version: 1.4.0
Summary: EMIL DiscountService
Home-page: UNKNOWN
Author: Contact us
Author-email: kontakt@emil.de
License: UNKNOWN
Keywords: OpenAPI,OpenAPI-Generator,EMIL DiscountService
Platform: UNKNOWN
Requires-Python: >=3.6
